{
  "date": "2026-04-11",
  "analyzed_at": "2026-05-18T02:01:14.766Z",
  "ligas": [
    "LCK",
    "LPL",
    "LEC",
    "CBLOL",
    "LCS"
  ],
  "count": 24,
  "results": [
    {
      "league": "LCK",
      "match_id": "115548128962906307",
      "game_id": "115548128962906308",
      "map_number": 1,
      "team_blue": "KRX",
      "team_red": "NS",
      "kills_blue": 24,
      "kills_red": 11,
      "total_kills": 35,
      "sup_blue": "Neeko",
      "sup_red": "Anivia",
      "peel_count": 0,
      "peel_bucket": "0peel",
      "flex_engages": [],
      "trigger_type": null,
      "matchup_fair": 31.5,
      "fair_source": "livestats_team_avg(team+team)/2",
      "fair_raw": 62.82,
      "fair_adjusted": 31.41,
      "blue_avg": 30.68,
      "red_avg": 32.14,
      "blue_sample_n": 31,
      "red_sample_n": 28,
      "league_baseline": 29.46,
      "vs_league": 1.95,
      "under_hit": false
    },
    {
      "league": "LCK",
      "match_id": "115548128962906307",
      "game_id": "115548128962906309",
      "map_number": 2,
      "team_blue": "KRX",
      "team_red": "NS",
      "kills_blue": 14,
      "kills_red": 7,
      "total_kills": 21,
      "sup_blue": "Alistar",
      "sup_red": "Nautilus",
      "peel_count": 0,
      "peel_bucket": "0peel",
      "flex_engages": [
        "Alistar"
      ],
      "trigger_type": null,
      "matchup_fair": 31.5,
      "fair_source": "livestats_team_avg(team+team)/2",
      "fair_raw": 63.77,
      "fair_adjusted": 31.89,
      "blue_avg": 31.13,
      "red_avg": 32.64,
      "blue_sample_n": 31,
      "red_sample_n": 28,
      "league_baseline": 29.46,
      "vs_league": 2.43,
      "under_hit": true
    },
    {
      "league": "LCK",
      "match_id": "115548128962906271",
      "game_id": "115548128962906272",
      "map_number": 1,
      "team_blue": "DK",
      "team_red": "GEN",
      "kills_blue": 13,
      "kills_red": 6,
      "total_kills": 19,
      "sup_blue": "Bard",
      "sup_red": "Pyke",
      "peel_count": 0,
      "peel_bucket": "0peel",
      "flex_engages": [
        "Bard"
      ],
      "trigger_type": null,
      "matchup_fair": 27.5,
      "fair_source": "livestats_team_avg(team+team)/2",
      "fair_raw": 55.75,
      "fair_adjusted": 27.87,
      "blue_avg": 26.17,
      "red_avg": 29.58,
      "blue_sample_n": 30,
      "red_sample_n": 31,
      "league_baseline": 29.46,
      "vs_league": -1.59,
      "under_hit": true
    },
    {
      "league": "LCK",
      "match_id": "115548128962906271",
      "game_id": "115548128962906273",
      "map_number": 2,
      "team_blue": "DK",
      "team_red": "GEN",
      "kills_blue": 6,
      "kills_red": 17,
      "total_kills": 23,
      "sup_blue": "Seraphine",
      "sup_red": "Renata",
      "peel_count": 2,
      "peel_bucket": "2peel",
      "flex_engages": [],
      "trigger_type": "2peel",
      "matchup_fair": 27.5,
      "fair_source": "livestats_team_avg(team+team)/2",
      "fair_raw": 55.48,
      "fair_adjusted": 27.74,
      "blue_avg": 26.03,
      "red_avg": 29.45,
      "blue_sample_n": 30,
      "red_sample_n": 31,
      "league_baseline": 29.46,
      "vs_league": -1.72,
      "under_hit": true
    },
    {
      "league": "LPL",
      "match_id": "115615924499588605",
      "game_id": "115615924499588606",
      "map_number": 1,
      "team_blue": "WE",
      "team_red": "IG",
      "kills_blue": 23,
      "kills_red": 10,
      "total_kills": 33,
      "sup_blue": "Seraphine",
      "sup_red": "Neeko",
      "peel_count": 1,
      "peel_bucket": "1peel",
      "flex_engages": [],
      "trigger_type": null,
      "matchup_fair": 28.5,
      "fair_source": "livestats_team_avg(team+team)/2",
      "fair_raw": 57.46,
      "fair_adjusted": 28.73,
      "blue_avg": 27.61,
      "red_avg": 29.85,
      "blue_sample_n": 31,
      "red_sample_n": 33,
      "league_baseline": 27.73,
      "vs_league": 1,
      "under_hit": false
    },
    {
      "league": "LPL",
      "match_id": "115615924499588605",
      "game_id": "115615926685695521",
      "map_number": 2,
      "team_blue": "WE",
      "team_red": "IG",
      "kills_blue": 16,
      "kills_red": 8,
      "total_kills": 24,
      "sup_blue": "Nami",
      "sup_red": "Lulu",
      "peel_count": 2,
      "peel_bucket": "2peel",
      "flex_engages": [],
      "trigger_type": "2peel",
      "matchup_fair": 29.5,
      "fair_source": "livestats_team_avg(team+team)/2",
      "fair_raw": 58.02,
      "fair_adjusted": 29.01,
      "blue_avg": 27.9,
      "red_avg": 30.12,
      "blue_sample_n": 31,
      "red_sample_n": 33,
      "league_baseline": 27.73,
      "vs_league": 1.28,
      "under_hit": true
    },
    {
      "league": "LPL",
      "match_id": "115615924499588615",
      "game_id": "115615924499588616",
      "map_number": 1,
      "team_blue": "TES",
      "team_red": "JDG",
      "kills_blue": 13,
      "kills_red": 18,
      "total_kills": 31,
      "sup_blue": "Neeko",
      "sup_red": "Lulu",
      "peel_count": 1,
      "peel_bucket": "1peel",
      "flex_engages": [],
      "trigger_type": null,
      "matchup_fair": 28.5,
      "fair_source": "livestats_team_avg(team+team)/2",
      "fair_raw": 57.17,
      "fair_adjusted": 28.58,
      "blue_avg": 29.86,
      "red_avg": 27.3,
      "blue_sample_n": 29,
      "red_sample_n": 33,
      "league_baseline": 27.73,
      "vs_league": 0.85,
      "under_hit": false
    },
    {
      "league": "LPL",
      "match_id": "115615924499588615",
      "game_id": "115615926685695531",
      "map_number": 2,
      "team_blue": "TES",
      "team_red": "JDG",
      "kills_blue": 10,
      "kills_red": 18,
      "total_kills": 28,
      "sup_blue": "Bard",
      "sup_red": "Karma",
      "peel_count": 1,
      "peel_bucket": "1peel",
      "flex_engages": [
        "Bard"
      ],
      "trigger_type": "1peel+flex",
      "matchup_fair": 28.5,
      "fair_source": "livestats_team_avg(team+team)/2",
      "fair_raw": 57.36,
      "fair_adjusted": 28.68,
      "blue_avg": 29.97,
      "red_avg": 27.39,
      "blue_sample_n": 29,
      "red_sample_n": 33,
      "league_baseline": 27.73,
      "vs_league": 0.95,
      "under_hit": true
    },
    {
      "league": "LEC",
      "match_id": "115548668059523636",
      "game_id": "115548668059523637",
      "map_number": 1,
      "team_blue": "NAVI",
      "team_red": "TH",
      "kills_blue": 16,
      "kills_red": 6,
      "total_kills": 22,
      "sup_blue": "Bard",
      "sup_red": "Seraphine",
      "peel_count": 1,
      "peel_bucket": "1peel",
      "flex_engages": [
        "Bard"
      ],
      "trigger_type": "1peel+flex",
      "matchup_fair": 25.5,
      "fair_source": "livestats_team_avg(team+team)/2",
      "fair_raw": 51.42,
      "fair_adjusted": 25.71,
      "blue_avg": 28.1,
      "red_avg": 23.32,
      "blue_sample_n": 20,
      "red_sample_n": 19,
      "league_baseline": 27.87,
      "vs_league": -2.16,
      "under_hit": true
    },
    {
      "league": "LEC",
      "match_id": "115548668059523636",
      "game_id": "115548668059523638",
      "map_number": 2,
      "team_blue": "NAVI",
      "team_red": "TH",
      "kills_blue": 22,
      "kills_red": 6,
      "total_kills": 28,
      "sup_blue": "Lulu",
      "sup_red": "Rakan",
      "peel_count": 1,
      "peel_bucket": "1peel",
      "flex_engages": [
        "Rakan"
      ],
      "trigger_type": "1peel+flex",
      "matchup_fair": 25.5,
      "fair_source": "livestats_team_avg(team+team)/2",
      "fair_raw": 50.8,
      "fair_adjusted": 25.4,
      "blue_avg": 27.8,
      "red_avg": 23,
      "blue_sample_n": 20,
      "red_sample_n": 19,
      "league_baseline": 27.87,
      "vs_league": -2.47,
      "under_hit": false
    },
    {
      "league": "LEC",
      "match_id": "115548668059523728",
      "game_id": "115548668059523729",
      "map_number": 1,
      "team_blue": "VIT",
      "team_red": "G2",
      "kills_blue": 19,
      "kills_red": 14,
      "total_kills": 33,
      "sup_blue": "Bard",
      "sup_red": "Lulu",
      "peel_count": 1,
      "peel_bucket": "1peel",
      "flex_engages": [
        "Bard"
      ],
      "trigger_type": "1peel+flex",
      "matchup_fair": 25.5,
      "fair_source": "livestats_team_avg(team+team)/2",
      "fair_raw": 51.98,
      "fair_adjusted": 25.99,
      "blue_avg": 26.48,
      "red_avg": 25.5,
      "blue_sample_n": 23,
      "red_sample_n": 20,
      "league_baseline": 27.87,
      "vs_league": -1.88,
      "under_hit": false
    },
    {
      "league": "LEC",
      "match_id": "115548668059523728",
      "game_id": "115548668059523730",
      "map_number": 2,
      "team_blue": "VIT",
      "team_red": "G2",
      "kills_blue": 7,
      "kills_red": 14,
      "total_kills": 21,
      "sup_blue": "Rell",
      "sup_red": "Seraphine",
      "peel_count": 1,
      "peel_bucket": "1peel",
      "flex_engages": [],
      "trigger_type": null,
      "matchup_fair": 26.5,
      "fair_source": "livestats_team_avg(team+team)/2",
      "fair_raw": 53.1,
      "fair_adjusted": 26.55,
      "blue_avg": 27,
      "red_avg": 26.1,
      "blue_sample_n": 23,
      "red_sample_n": 20,
      "league_baseline": 27.87,
      "vs_league": -1.32,
      "under_hit": true
    },
    {
      "league": "LEC",
      "match_id": "115548668059523728",
      "game_id": "115548668059523731",
      "map_number": 3,
      "team_blue": "VIT",
      "team_red": "G2",
      "kills_blue": 1,
      "kills_red": 8,
      "total_kills": 9,
      "sup_blue": "Milio",
      "sup_red": "Nami",
      "peel_count": 2,
      "peel_bucket": "2peel",
      "flex_engages": [],
      "trigger_type": "2peel",
      "matchup_fair": 27.5,
      "fair_source": "livestats_team_avg(team+team)/2",
      "fair_raw": 54.22,
      "fair_adjusted": 27.11,
      "blue_avg": 27.52,
      "red_avg": 26.7,
      "blue_sample_n": 23,
      "red_sample_n": 20,
      "league_baseline": 27.87,
      "vs_league": -0.76,
      "under_hit": true
    },
    {
      "league": "LEC",
      "match_id": "115548668059523776",
      "game_id": "115548668059523777",
      "map_number": 1,
      "team_blue": "SK",
      "team_red": "MKOI",
      "kills_blue": 15,
      "kills_red": 22,
      "total_kills": 37,
      "sup_blue": "Nautilus",
      "sup_red": "Karma",
      "peel_count": 1,
      "peel_bucket": "1peel",
      "flex_engages": [],
      "trigger_type": null,
      "matchup_fair": 30.5,
      "fair_source": "livestats_team_avg(team+team)/2",
      "fair_raw": 61.65,
      "fair_adjusted": 30.83,
      "blue_avg": 31.2,
      "red_avg": 30.45,
      "blue_sample_n": 20,
      "red_sample_n": 22,
      "league_baseline": 27.87,
      "vs_league": 2.96,
      "under_hit": false
    },
    {
      "league": "LEC",
      "match_id": "115548668059523776",
      "game_id": "115548668059523778",
      "map_number": 2,
      "team_blue": "SK",
      "team_red": "MKOI",
      "kills_blue": 12,
      "kills_red": 8,
      "total_kills": 20,
      "sup_blue": "Lulu",
      "sup_red": "Nami",
      "peel_count": 2,
      "peel_bucket": "2peel",
      "flex_engages": [],
      "trigger_type": "2peel",
      "matchup_fair": 31.5,
      "fair_source": "livestats_team_avg(team+team)/2",
      "fair_raw": 63.28,
      "fair_adjusted": 31.64,
      "blue_avg": 32.05,
      "red_avg": 31.23,
      "blue_sample_n": 20,
      "red_sample_n": 22,
      "league_baseline": 27.87,
      "vs_league": 3.77,
      "under_hit": true
    },
    {
      "league": "CBLOL",
      "match_id": "115565670260116201",
      "game_id": "115565670260116202",
      "map_number": 1,
      "team_blue": "LEV",
      "team_red": "FUR",
      "kills_blue": 15,
      "kills_red": 23,
      "total_kills": 38,
      "sup_blue": "Bard",
      "sup_red": "Anivia",
      "peel_count": 0,
      "peel_bucket": "0peel",
      "flex_engages": [
        "Bard"
      ],
      "trigger_type": null,
      "matchup_fair": 27.5,
      "fair_source": "livestats_team_avg(team+team)/2",
      "fair_raw": 55.71,
      "fair_adjusted": 27.85,
      "blue_avg": 28.86,
      "red_avg": 26.85,
      "blue_sample_n": 14,
      "red_sample_n": 20,
      "league_baseline": 27.76,
      "vs_league": 0.09,
      "under_hit": false
    },
    {
      "league": "CBLOL",
      "match_id": "115565670260116201",
      "game_id": "115565670260116203",
      "map_number": 2,
      "team_blue": "LEV",
      "team_red": "FUR",
      "kills_blue": 5,
      "kills_red": 19,
      "total_kills": 24,
      "sup_blue": "Neeko",
      "sup_red": "Nami",
      "peel_count": 1,
      "peel_bucket": "1peel",
      "flex_engages": [],
      "trigger_type": null,
      "matchup_fair": 28.5,
      "fair_source": "livestats_team_avg(team+team)/2",
      "fair_raw": 57.41,
      "fair_adjusted": 28.7,
      "blue_avg": 29.86,
      "red_avg": 27.55,
      "blue_sample_n": 14,
      "red_sample_n": 20,
      "league_baseline": 27.76,
      "vs_league": 0.94,
      "under_hit": true
    },
    {
      "league": "CBLOL",
      "match_id": "115565670260116273",
      "game_id": "115565670260116274",
      "map_number": 1,
      "team_blue": "PAIN",
      "team_red": "RED",
      "kills_blue": 8,
      "kills_red": 27,
      "total_kills": 35,
      "sup_blue": "Seraphine",
      "sup_red": "Bard",
      "peel_count": 1,
      "peel_bucket": "1peel",
      "flex_engages": [
        "Bard"
      ],
      "trigger_type": "1peel+flex",
      "matchup_fair": 27.5,
      "fair_source": "livestats_team_avg(team+team)/2",
      "fair_raw": 55.81,
      "fair_adjusted": 27.9,
      "blue_avg": 26.14,
      "red_avg": 29.67,
      "blue_sample_n": 14,
      "red_sample_n": 18,
      "league_baseline": 27.76,
      "vs_league": 0.14,
      "under_hit": false
    },
    {
      "league": "CBLOL",
      "match_id": "115565670260116273",
      "game_id": "115565670260116275",
      "map_number": 2,
      "team_blue": "PAIN",
      "team_red": "RED",
      "kills_blue": 24,
      "kills_red": 8,
      "total_kills": 32,
      "sup_blue": "Rakan",
      "sup_red": "Neeko",
      "peel_count": 0,
      "peel_bucket": "0peel",
      "flex_engages": [
        "Rakan"
      ],
      "trigger_type": null,
      "matchup_fair": 28.5,
      "fair_source": "livestats_team_avg(team+team)/2",
      "fair_raw": 56.19,
      "fair_adjusted": 28.1,
      "blue_avg": 26.36,
      "red_avg": 29.83,
      "blue_sample_n": 14,
      "red_sample_n": 18,
      "league_baseline": 27.76,
      "vs_league": 0.34,
      "under_hit": false
    },
    {
      "league": "LCS",
      "match_id": "115564793879469284",
      "game_id": "115564793879469285",
      "map_number": 1,
      "team_blue": "TLAW",
      "team_red": "SR",
      "kills_blue": 25,
      "kills_red": 2,
      "total_kills": 27,
      "sup_blue": "Seraphine",
      "sup_red": "Nami",
      "peel_count": 2,
      "peel_bucket": "2peel",
      "flex_engages": [],
      "trigger_type": "2peel",
      "matchup_fair": 28.5,
      "fair_source": "livestats_team_avg(team+team)/2",
      "fair_raw": 56.69,
      "fair_adjusted": 28.34,
      "blue_avg": 27.35,
      "red_avg": 29.33,
      "blue_sample_n": 17,
      "red_sample_n": 12,
      "league_baseline": 26.77,
      "vs_league": 1.57,
      "under_hit": true
    },
    {
      "league": "LCS",
      "match_id": "115564793879469284",
      "game_id": "115564793879469286",
      "map_number": 2,
      "team_blue": "TLAW",
      "team_red": "SR",
      "kills_blue": 17,
      "kills_red": 15,
      "total_kills": 32,
      "sup_blue": "Rakan",
      "sup_red": "Neeko",
      "peel_count": 0,
      "peel_bucket": "0peel",
      "flex_engages": [
        "Rakan"
      ],
      "trigger_type": null,
      "matchup_fair": 27.5,
      "fair_source": "livestats_team_avg(team+team)/2",
      "fair_raw": 55.98,
      "fair_adjusted": 27.99,
      "blue_avg": 27.06,
      "red_avg": 28.92,
      "blue_sample_n": 17,
      "red_sample_n": 12,
      "league_baseline": 26.77,
      "vs_league": 1.22,
      "under_hit": false
    },
    {
      "league": "LCS",
      "match_id": "115564793879403700",
      "game_id": "115564793879403701",
      "map_number": 1,
      "team_blue": "LYON",
      "team_red": "DIG",
      "kills_blue": 6,
      "kills_red": 13,
      "total_kills": 19,
      "sup_blue": "Lulu",
      "sup_red": "Nami",
      "peel_count": 2,
      "peel_bucket": "2peel",
      "flex_engages": [],
      "trigger_type": "2peel",
      "matchup_fair": 25.5,
      "fair_source": "livestats_team_avg(team+team)/2",
      "fair_raw": 51.86,
      "fair_adjusted": 25.93,
      "blue_avg": 27.24,
      "red_avg": 24.63,
      "blue_sample_n": 17,
      "red_sample_n": 16,
      "league_baseline": 26.77,
      "vs_league": -0.84,
      "under_hit": true
    },
    {
      "league": "LCS",
      "match_id": "115564793879403700",
      "game_id": "115564793879403702",
      "map_number": 2,
      "team_blue": "LYON",
      "team_red": "DIG",
      "kills_blue": 4,
      "kills_red": 10,
      "total_kills": 14,
      "sup_blue": "Neeko",
      "sup_red": "Lux",
      "peel_count": 0,
      "peel_bucket": "0peel",
      "flex_engages": [],
      "trigger_type": null,
      "matchup_fair": 26.5,
      "fair_source": "livestats_team_avg(team+team)/2",
      "fair_raw": 52.47,
      "fair_adjusted": 26.23,
      "blue_avg": 27.53,
      "red_avg": 24.94,
      "blue_sample_n": 17,
      "red_sample_n": 16,
      "league_baseline": 26.77,
      "vs_league": -0.54,
      "under_hit": true
    },
    {
      "league": "LCS",
      "match_id": "115564793879403700",
      "game_id": "115564793879403703",
      "map_number": 3,
      "team_blue": "LYON",
      "team_red": "DIG",
      "kills_blue": 22,
      "kills_red": 7,
      "total_kills": 29,
      "sup_blue": "Rakan",
      "sup_red": "Karma",
      "peel_count": 1,
      "peel_bucket": "1peel",
      "flex_engages": [
        "Rakan"
      ],
      "trigger_type": "1peel+flex",
      "matchup_fair": 25.5,
      "fair_source": "livestats_team_avg(team+team)/2",
      "fair_raw": 50.65,
      "fair_adjusted": 25.32,
      "blue_avg": 26.65,
      "red_avg": 24,
      "blue_sample_n": 17,
      "red_sample_n": 16,
      "league_baseline": 26.77,
      "vs_league": -1.45,
      "under_hit": false
    }
  ]
}