{
  "date": "2026-04-25",
  "analyzed_at": "2026-05-18T12:38:07.121Z",
  "ligas": [
    "LCK",
    "LPL",
    "LEC",
    "CBLOL",
    "LCS"
  ],
  "count": 25,
  "results": [
    {
      "league": "LCK",
      "match_id": "115548128962840639",
      "game_id": "115548128962840640",
      "map_number": 1,
      "team_blue": "BRO",
      "team_red": "T1",
      "kills_blue": 25,
      "kills_red": 20,
      "total_kills": 45,
      "sup_blue": "Elise",
      "sup_red": "Neeko",
      "peel_count": 0,
      "peel_bucket": "0peel",
      "flex_engages": [],
      "trigger_type": null,
      "matchup_fair": 29.5,
      "fair_source": "livestats_team_avg(team+team)/2",
      "fair_raw": 58.24,
      "fair_adjusted": 29.12,
      "blue_avg": 27.69,
      "red_avg": 30.55,
      "blue_sample_n": 29,
      "red_sample_n": 29,
      "league_baseline": 29.46,
      "vs_league": -0.34,
      "under_hit": false
    },
    {
      "league": "LCK",
      "match_id": "115548128962840639",
      "game_id": "115548128962840641",
      "map_number": 2,
      "team_blue": "BRO",
      "team_red": "T1",
      "kills_blue": 20,
      "kills_red": 17,
      "total_kills": 37,
      "sup_blue": "Morgana",
      "sup_red": "Leona",
      "peel_count": 0,
      "peel_bucket": "0peel",
      "flex_engages": [],
      "trigger_type": null,
      "matchup_fair": 29.5,
      "fair_source": "livestats_team_avg(team+team)/2",
      "fair_raw": 58.79,
      "fair_adjusted": 29.4,
      "blue_avg": 27.97,
      "red_avg": 30.83,
      "blue_sample_n": 29,
      "red_sample_n": 29,
      "league_baseline": 29.46,
      "vs_league": -0.06,
      "under_hit": false
    },
    {
      "league": "LCK",
      "match_id": "115548128962906235",
      "game_id": "115548128962906236",
      "map_number": 1,
      "team_blue": "DK",
      "team_red": "DNS",
      "kills_blue": 15,
      "kills_red": 6,
      "total_kills": 21,
      "sup_blue": "Karma",
      "sup_red": "Nautilus",
      "peel_count": 1,
      "peel_bucket": "1peel",
      "flex_engages": [],
      "trigger_type": null,
      "matchup_fair": 26.5,
      "fair_source": "livestats_team_avg(team+team)/2",
      "fair_raw": 52.47,
      "fair_adjusted": 26.24,
      "blue_avg": 26.1,
      "red_avg": 26.37,
      "blue_sample_n": 30,
      "red_sample_n": 27,
      "league_baseline": 29.46,
      "vs_league": -3.22,
      "under_hit": true
    },
    {
      "league": "LCK",
      "match_id": "115548128962906235",
      "game_id": "115548128962906237",
      "map_number": 2,
      "team_blue": "DK",
      "team_red": "DNS",
      "kills_blue": 17,
      "kills_red": 10,
      "total_kills": 27,
      "sup_blue": "Lulu",
      "sup_red": "Neeko",
      "peel_count": 1,
      "peel_bucket": "1peel",
      "flex_engages": [],
      "trigger_type": null,
      "matchup_fair": 26.5,
      "fair_source": "livestats_team_avg(team+team)/2",
      "fair_raw": 52.05,
      "fair_adjusted": 26.02,
      "blue_avg": 25.9,
      "red_avg": 26.15,
      "blue_sample_n": 30,
      "red_sample_n": 27,
      "league_baseline": 29.46,
      "vs_league": -3.44,
      "under_hit": false
    },
    {
      "league": "LPL",
      "match_id": "115615924499588621",
      "game_id": "115615924499588622",
      "map_number": 1,
      "team_blue": "TES",
      "team_red": "NIP",
      "kills_blue": 19,
      "kills_red": 14,
      "total_kills": 33,
      "sup_blue": "Seraphine",
      "sup_red": "Milio",
      "peel_count": 2,
      "peel_bucket": "2peel",
      "flex_engages": [],
      "trigger_type": "2peel",
      "matchup_fair": 28.5,
      "fair_source": "livestats_team_avg(team+team)/2",
      "fair_raw": 57.7,
      "fair_adjusted": 28.85,
      "blue_avg": 29.79,
      "red_avg": 27.9,
      "blue_sample_n": 29,
      "red_sample_n": 31,
      "league_baseline": 27.73,
      "vs_league": 1.12,
      "under_hit": false
    },
    {
      "league": "LPL",
      "match_id": "115615924499588621",
      "game_id": "115615926685695537",
      "map_number": 2,
      "team_blue": "TES",
      "team_red": "NIP",
      "kills_blue": 18,
      "kills_red": 13,
      "total_kills": 31,
      "sup_blue": "Lulu",
      "sup_red": "Nami",
      "peel_count": 2,
      "peel_bucket": "2peel",
      "flex_engages": [],
      "trigger_type": "2peel",
      "matchup_fair": 28.5,
      "fair_source": "livestats_team_avg(team+team)/2",
      "fair_raw": 57.83,
      "fair_adjusted": 28.91,
      "blue_avg": 29.86,
      "red_avg": 27.97,
      "blue_sample_n": 29,
      "red_sample_n": 31,
      "league_baseline": 27.73,
      "vs_league": 1.18,
      "under_hit": false
    },
    {
      "league": "LPL",
      "match_id": "115615924499588613",
      "game_id": "115615924499588614",
      "map_number": 1,
      "team_blue": "WE",
      "team_red": "JDG",
      "kills_blue": 21,
      "kills_red": 7,
      "total_kills": 28,
      "sup_blue": "Seraphine",
      "sup_red": "Neeko",
      "peel_count": 1,
      "peel_bucket": "1peel",
      "flex_engages": [],
      "trigger_type": null,
      "matchup_fair": 27.5,
      "fair_source": "livestats_team_avg(team+team)/2",
      "fair_raw": 55.17,
      "fair_adjusted": 27.58,
      "blue_avg": 27.77,
      "red_avg": 27.39,
      "blue_sample_n": 31,
      "red_sample_n": 33,
      "league_baseline": 27.73,
      "vs_league": -0.15,
      "under_hit": false
    },
    {
      "league": "LPL",
      "match_id": "115615924499588613",
      "game_id": "115615926685695529",
      "map_number": 2,
      "team_blue": "WE",
      "team_red": "JDG",
      "kills_blue": 18,
      "kills_red": 6,
      "total_kills": 24,
      "sup_blue": "Milio",
      "sup_red": "Renata",
      "peel_count": 2,
      "peel_bucket": "2peel",
      "flex_engages": [],
      "trigger_type": "2peel",
      "matchup_fair": 27.5,
      "fair_source": "livestats_team_avg(team+team)/2",
      "fair_raw": 55.42,
      "fair_adjusted": 27.71,
      "blue_avg": 27.9,
      "red_avg": 27.52,
      "blue_sample_n": 31,
      "red_sample_n": 33,
      "league_baseline": 27.73,
      "vs_league": -0.02,
      "under_hit": true
    },
    {
      "league": "LPL",
      "match_id": "115615926677831083",
      "game_id": "115615926677831084",
      "map_number": 1,
      "team_blue": "WBG",
      "team_red": "AL",
      "kills_blue": 5,
      "kills_red": 21,
      "total_kills": 26,
      "sup_blue": "Neeko",
      "sup_red": "Bard",
      "peel_count": 0,
      "peel_bucket": "0peel",
      "flex_engages": [
        "Bard"
      ],
      "trigger_type": null,
      "matchup_fair": 26.5,
      "fair_source": "livestats_team_avg(team+team)/2",
      "fair_raw": 53.87,
      "fair_adjusted": 26.94,
      "blue_avg": 27.91,
      "red_avg": 25.97,
      "blue_sample_n": 32,
      "red_sample_n": 30,
      "league_baseline": 27.73,
      "vs_league": -0.79,
      "under_hit": true
    },
    {
      "league": "LPL",
      "match_id": "115615926677831083",
      "game_id": "115615926677896621",
      "map_number": 2,
      "team_blue": "WBG",
      "team_red": "AL",
      "kills_blue": 3,
      "kills_red": 22,
      "total_kills": 25,
      "sup_blue": "Seraphine",
      "sup_red": "Karma",
      "peel_count": 2,
      "peel_bucket": "2peel",
      "flex_engages": [],
      "trigger_type": "2peel",
      "matchup_fair": 26.5,
      "fair_source": "livestats_team_avg(team+team)/2",
      "fair_raw": 53.94,
      "fair_adjusted": 26.97,
      "blue_avg": 27.94,
      "red_avg": 26,
      "blue_sample_n": 32,
      "red_sample_n": 30,
      "league_baseline": 27.73,
      "vs_league": -0.76,
      "under_hit": true
    },
    {
      "league": "LPL",
      "match_id": "115615926677831083",
      "game_id": "115615926677896622",
      "map_number": 3,
      "team_blue": "WBG",
      "team_red": "AL",
      "kills_blue": 7,
      "kills_red": 15,
      "total_kills": 22,
      "sup_blue": "Lulu",
      "sup_red": "Milio",
      "peel_count": 2,
      "peel_bucket": "2peel",
      "flex_engages": [],
      "trigger_type": "2peel",
      "matchup_fair": 27.5,
      "fair_source": "livestats_team_avg(team+team)/2",
      "fair_raw": 54.13,
      "fair_adjusted": 27.07,
      "blue_avg": 28.03,
      "red_avg": 26.1,
      "blue_sample_n": 32,
      "red_sample_n": 30,
      "league_baseline": 27.73,
      "vs_league": -0.66,
      "under_hit": true
    },
    {
      "league": "LEC",
      "match_id": "115548668059523692",
      "game_id": "115548668059523693",
      "map_number": 1,
      "team_blue": "NAVI",
      "team_red": "FNC",
      "kills_blue": 7,
      "kills_red": 14,
      "total_kills": 21,
      "sup_blue": "Karma",
      "sup_red": "Seraphine",
      "peel_count": 2,
      "peel_bucket": "2peel",
      "flex_engages": [],
      "trigger_type": "2peel",
      "matchup_fair": 27.5,
      "fair_source": "livestats_team_avg(team+team)/2",
      "fair_raw": 54.55,
      "fair_adjusted": 27.27,
      "blue_avg": 28.15,
      "red_avg": 26.4,
      "blue_sample_n": 20,
      "red_sample_n": 20,
      "league_baseline": 27.87,
      "vs_league": -0.6,
      "under_hit": true
    },
    {
      "league": "LEC",
      "match_id": "115548668059523692",
      "game_id": "115548668059523694",
      "map_number": 2,
      "team_blue": "NAVI",
      "team_red": "FNC",
      "kills_blue": 13,
      "kills_red": 7,
      "total_kills": 20,
      "sup_blue": "Bard",
      "sup_red": "Nami",
      "peel_count": 1,
      "peel_bucket": "1peel",
      "flex_engages": [
        "Bard"
      ],
      "trigger_type": "1peel+flex",
      "matchup_fair": 27.5,
      "fair_source": "livestats_team_avg(team+team)/2",
      "fair_raw": 54.65,
      "fair_adjusted": 27.32,
      "blue_avg": 28.2,
      "red_avg": 26.45,
      "blue_sample_n": 20,
      "red_sample_n": 20,
      "league_baseline": 27.87,
      "vs_league": -0.55,
      "under_hit": true
    },
    {
      "league": "LEC",
      "match_id": "115548668059523692",
      "game_id": "115548668059523695",
      "map_number": 3,
      "team_blue": "NAVI",
      "team_red": "FNC",
      "kills_blue": 11,
      "kills_red": 10,
      "total_kills": 21,
      "sup_blue": "Rakan",
      "sup_red": "Neeko",
      "peel_count": 0,
      "peel_bucket": "0peel",
      "flex_engages": [
        "Rakan"
      ],
      "trigger_type": null,
      "matchup_fair": 27.5,
      "fair_source": "livestats_team_avg(team+team)/2",
      "fair_raw": 54.55,
      "fair_adjusted": 27.27,
      "blue_avg": 28.15,
      "red_avg": 26.4,
      "blue_sample_n": 20,
      "red_sample_n": 20,
      "league_baseline": 27.87,
      "vs_league": -0.6,
      "under_hit": true
    },
    {
      "league": "LEC",
      "match_id": "115548668059523748",
      "game_id": "115548668059523749",
      "map_number": 1,
      "team_blue": "KC",
      "team_red": "SHFT",
      "kills_blue": 20,
      "kills_red": 5,
      "total_kills": 25,
      "sup_blue": "Bard",
      "sup_red": "Karma",
      "peel_count": 1,
      "peel_bucket": "1peel",
      "flex_engages": [
        "Bard"
      ],
      "trigger_type": "1peel+flex",
      "matchup_fair": 30.5,
      "fair_source": "livestats_team_avg(team+team)/2",
      "fair_raw": 61.52,
      "fair_adjusted": 30.76,
      "blue_avg": 30.47,
      "red_avg": 31.05,
      "blue_sample_n": 19,
      "red_sample_n": 20,
      "league_baseline": 27.87,
      "vs_league": 2.89,
      "under_hit": true
    },
    {
      "league": "LEC",
      "match_id": "115548668059523748",
      "game_id": "115548668059523750",
      "map_number": 2,
      "team_blue": "KC",
      "team_red": "SHFT",
      "kills_blue": 18,
      "kills_red": 20,
      "total_kills": 38,
      "sup_blue": "Milio",
      "sup_red": "Nami",
      "peel_count": 2,
      "peel_bucket": "2peel",
      "flex_engages": [],
      "trigger_type": "2peel",
      "matchup_fair": 30.5,
      "fair_source": "livestats_team_avg(team+team)/2",
      "fair_raw": 60.19,
      "fair_adjusted": 30.09,
      "blue_avg": 29.79,
      "red_avg": 30.4,
      "blue_sample_n": 19,
      "red_sample_n": 20,
      "league_baseline": 27.87,
      "vs_league": 2.22,
      "under_hit": false
    },
    {
      "league": "LEC",
      "match_id": "115548668059523748",
      "game_id": "115548668059523751",
      "map_number": 3,
      "team_blue": "KC",
      "team_red": "SHFT",
      "kills_blue": 27,
      "kills_red": 17,
      "total_kills": 44,
      "sup_blue": "Lulu",
      "sup_red": "Neeko",
      "peel_count": 1,
      "peel_bucket": "1peel",
      "flex_engages": [],
      "trigger_type": null,
      "matchup_fair": 29.5,
      "fair_source": "livestats_team_avg(team+team)/2",
      "fair_raw": 59.57,
      "fair_adjusted": 29.79,
      "blue_avg": 29.47,
      "red_avg": 30.1,
      "blue_sample_n": 19,
      "red_sample_n": 20,
      "league_baseline": 27.87,
      "vs_league": 1.92,
      "under_hit": false
    },
    {
      "league": "CBLOL",
      "match_id": "115565670260116253",
      "game_id": "115565670260116254",
      "map_number": 1,
      "team_blue": "LOS",
      "team_red": "RED",
      "kills_blue": 15,
      "kills_red": 26,
      "total_kills": 41,
      "sup_blue": "Nami",
      "sup_red": "Neeko",
      "peel_count": 1,
      "peel_bucket": "1peel",
      "flex_engages": [],
      "trigger_type": null,
      "matchup_fair": 28.5,
      "fair_source": "livestats_team_avg(team+team)/2",
      "fair_raw": 57.06,
      "fair_adjusted": 28.53,
      "blue_avg": 27.73,
      "red_avg": 29.33,
      "blue_sample_n": 22,
      "red_sample_n": 18,
      "league_baseline": 27.76,
      "vs_league": 0.77,
      "under_hit": false
    },
    {
      "league": "CBLOL",
      "match_id": "115565670260116253",
      "game_id": "115565670260116255",
      "map_number": 2,
      "team_blue": "LOS",
      "team_red": "RED",
      "kills_blue": 19,
      "kills_red": 9,
      "total_kills": 28,
      "sup_blue": "Nautilus",
      "sup_red": "Lulu",
      "peel_count": 1,
      "peel_bucket": "1peel",
      "flex_engages": [],
      "trigger_type": null,
      "matchup_fair": 29.5,
      "fair_source": "livestats_team_avg(team+team)/2",
      "fair_raw": 58.37,
      "fair_adjusted": 29.19,
      "blue_avg": 28.32,
      "red_avg": 30.06,
      "blue_sample_n": 22,
      "red_sample_n": 18,
      "league_baseline": 27.76,
      "vs_league": 1.43,
      "under_hit": true
    },
    {
      "league": "CBLOL",
      "match_id": "115565670260050653",
      "game_id": "115565670260050654",
      "map_number": 1,
      "team_blue": "PAIN",
      "team_red": "FX",
      "kills_blue": 14,
      "kills_red": 25,
      "total_kills": 39,
      "sup_blue": "Neeko",
      "sup_red": "Bard",
      "peel_count": 0,
      "peel_bucket": "0peel",
      "flex_engages": [
        "Bard"
      ],
      "trigger_type": null,
      "matchup_fair": 26.5,
      "fair_source": "livestats_team_avg(team+team)/2",
      "fair_raw": 52.48,
      "fair_adjusted": 26.24,
      "blue_avg": 25.86,
      "red_avg": 26.63,
      "blue_sample_n": 14,
      "red_sample_n": 24,
      "league_baseline": 27.76,
      "vs_league": -1.52,
      "under_hit": false
    },
    {
      "league": "CBLOL",
      "match_id": "115565670260050653",
      "game_id": "115565670260050655",
      "map_number": 2,
      "team_blue": "PAIN",
      "team_red": "FX",
      "kills_blue": 14,
      "kills_red": 6,
      "total_kills": 20,
      "sup_blue": "Nami",
      "sup_red": "Lulu",
      "peel_count": 2,
      "peel_bucket": "2peel",
      "flex_engages": [],
      "trigger_type": "2peel",
      "matchup_fair": 27.5,
      "fair_source": "livestats_team_avg(team+team)/2",
      "fair_raw": 54.63,
      "fair_adjusted": 27.32,
      "blue_avg": 27.21,
      "red_avg": 27.42,
      "blue_sample_n": 14,
      "red_sample_n": 24,
      "league_baseline": 27.76,
      "vs_league": -0.44,
      "under_hit": true
    },
    {
      "league": "LCS",
      "match_id": "115564793879403696",
      "game_id": "115564793879403697",
      "map_number": 1,
      "team_blue": "DIG",
      "team_red": "FLY",
      "kills_blue": 8,
      "kills_red": 13,
      "total_kills": 21,
      "sup_blue": "Lulu",
      "sup_red": "Seraphine",
      "peel_count": 2,
      "peel_bucket": "2peel",
      "flex_engages": [],
      "trigger_type": "2peel",
      "matchup_fair": 26.5,
      "fair_source": "livestats_team_avg(team+team)/2",
      "fair_raw": 53.88,
      "fair_adjusted": 26.94,
      "blue_avg": 24.5,
      "red_avg": 29.38,
      "blue_sample_n": 16,
      "red_sample_n": 16,
      "league_baseline": 26.77,
      "vs_league": 0.17,
      "under_hit": true
    },
    {
      "league": "LCS",
      "match_id": "115564793879403696",
      "game_id": "115564793879403698",
      "map_number": 2,
      "team_blue": "DIG",
      "team_red": "FLY",
      "kills_blue": 27,
      "kills_red": 16,
      "total_kills": 43,
      "sup_blue": "Bard",
      "sup_red": "Alistar",
      "peel_count": 0,
      "peel_bucket": "0peel",
      "flex_engages": [
        "Bard",
        "Alistar"
      ],
      "trigger_type": null,
      "matchup_fair": 25.5,
      "fair_source": "livestats_team_avg(team+team)/2",
      "fair_raw": 51.13,
      "fair_adjusted": 25.56,
      "blue_avg": 23.13,
      "red_avg": 28,
      "blue_sample_n": 16,
      "red_sample_n": 16,
      "league_baseline": 26.77,
      "vs_league": -1.21,
      "under_hit": false
    },
    {
      "league": "LCS",
      "match_id": "115564793879403684",
      "game_id": "115564793879403685",
      "map_number": 1,
      "team_blue": "SR",
      "team_red": "C9",
      "kills_blue": 8,
      "kills_red": 21,
      "total_kills": 29,
      "sup_blue": "Leona",
      "sup_red": "Rakan",
      "peel_count": 0,
      "peel_bucket": "0peel",
      "flex_engages": [
        "Rakan"
      ],
      "trigger_type": null,
      "matchup_fair": 27.5,
      "fair_source": "livestats_team_avg(team+team)/2",
      "fair_raw": 54.85,
      "fair_adjusted": 27.43,
      "blue_avg": 29.17,
      "red_avg": 25.69,
      "blue_sample_n": 12,
      "red_sample_n": 16,
      "league_baseline": 26.77,
      "vs_league": 0.66,
      "under_hit": false
    },
    {
      "league": "LCS",
      "match_id": "115564793879403684",
      "game_id": "115564793879403686",
      "map_number": 2,
      "team_blue": "SR",
      "team_red": "C9",
      "kills_blue": 21,
      "kills_red": 5,
      "total_kills": 26,
      "sup_blue": "Seraphine",
      "sup_red": "Nautilus",
      "peel_count": 1,
      "peel_bucket": "1peel",
      "flex_engages": [],
      "trigger_type": null,
      "matchup_fair": 27.5,
      "fair_source": "livestats_team_avg(team+team)/2",
      "fair_raw": 55.29,
      "fair_adjusted": 27.65,
      "blue_avg": 29.42,
      "red_avg": 25.88,
      "blue_sample_n": 12,
      "red_sample_n": 16,
      "league_baseline": 26.77,
      "vs_league": 0.88,
      "under_hit": true
    }
  ]
}